etebase/__init__.py
etebase/etebase_python.cpython-310-darwin.so
etebase-0.31.5.dist-info/LICENSE
etebase-0.31.5.dist-info/METADATA
etebase-0.31.5.dist-info/WHEEL
etebase-0.31.5.dist-info/top_level.txt
etebase-0.31.5.dist-info/RECORD
