Metadata-Version: 2.1
Name: etebase
Version: 0.31.5
Summary: Python client library for Etebase
Home-page: https://github.com/etesync/etebase-py
Author: Tom Hacohen
Author-email: tom@stosb.com
License: BSD-3-Clause
Keywords: etebase,encryption,sync,end-to-end encryption
Platform: UNKNOWN
Requires-Python: >=3
License-File: LICENSE
Requires-Dist: msgpack (>=1.0.0)
